{
  "genre": "live",
  "channels": [
    
    
    {
      "name": "Sony Live Events",
      "logo": "https://i.ibb.co/6RRJyNJq/image-2026-02-19-005319752.png",
      "link": "https://allinonereborn.xyz/events"
    },
    {
      "name": "T2O World Cup",
      "logo": "https://i.ibb.co/FkM5vGh6/Untitled-design-modified.png",
      "link": "https://crick-live-sooty.vercel.app/watch.html?id=Prime"
    },
    {
      "name": "Fancode",
      "logo": "https://i.ibb.co/5gtfpnwF/image-2026-02-19-005400348.png",
      "link": "https://freelivtv.ct.ws/fancode.html?i=2"
    }
    

  ]

}

